<?xml version="1.0" encoding="utf-8" ?>
<dwsync>
<file name="audio.png" server="wmrc//home/wmrc/www/" local="128481368270000000" remote="128481368270000000" />
<file name="blank.gif" server="wmrc//home/wmrc/www/" local="128543979200000000" remote="128543979200000000" />
<file name="css.png" server="wmrc//home/wmrc/www/" local="128481368270000000" remote="128481368270000000" />
<file name="default.png" server="wmrc//home/wmrc/www/" local="128481368270000000" remote="128481368270000000" />
<file name="doc.png" server="wmrc//home/wmrc/www/" local="128481368270000000" remote="128481368270000000" />
<file name="exe.png" server="wmrc//home/wmrc/www/" local="128481368270000000" remote="128481368270000000" />
<file name="html.png" server="wmrc//home/wmrc/www/" local="128481368270000000" remote="128481368270000000" />
<file name="js.png" server="wmrc//home/wmrc/www/" local="128481368270000000" remote="128481368270000000" />
<file name="pdf.png" server="wmrc//home/wmrc/www/" local="128481368270000000" remote="128481368270000000" />
<file name="rss.png" server="wmrc//home/wmrc/www/" local="128218503170000000" remote="128218503170000000" />
<file name="swf.png" server="wmrc//home/wmrc/www/" local="128481368270000000" remote="128481368270000000" />
<file name="tar.png" server="wmrc//home/wmrc/www/" local="128481368270000000" remote="128481368270000000" />
<file name="text.png" server="wmrc//home/wmrc/www/" local="128481368270000000" remote="128481368270000000" />
<file name="video.png" server="wmrc//home/wmrc/www/" local="128481368270000000" remote="128481368270000000" />
<file name="zip.png" server="wmrc//home/wmrc/www/" local="128481368270000000" remote="128481368270000000" />
<file name="audio.png" server="ftp.waverleymrc.org.au" local="128481368270000000" remote="128663407800000000" />
<file name="blank.gif" server="ftp.waverleymrc.org.au" local="128543979200000000" remote="128663407800000000" />
<file name="css.png" server="ftp.waverleymrc.org.au" local="128481368270000000" remote="128663407800000000" />
<file name="default.png" server="ftp.waverleymrc.org.au" local="128481368270000000" remote="128663408400000000" />
<file name="doc.png" server="ftp.waverleymrc.org.au" local="128481368270000000" remote="128663408400000000" />
<file name="exe.png" server="ftp.waverleymrc.org.au" local="128481368270000000" remote="128663408400000000" />
<file name="html.png" server="ftp.waverleymrc.org.au" local="128481368270000000" remote="128663408400000000" />
<file name="js.png" server="ftp.waverleymrc.org.au" local="128481368270000000" remote="128663408400000000" />
<file name="pdf.png" server="ftp.waverleymrc.org.au" local="128481368270000000" remote="128663408400000000" />
<file name="rss.png" server="ftp.waverleymrc.org.au" local="128218503170000000" remote="128663408400000000" />
<file name="swf.png" server="ftp.waverleymrc.org.au" local="128481368270000000" remote="128663408400000000" />
<file name="tar.png" server="ftp.waverleymrc.org.au" local="128481368270000000" remote="128663408400000000" />
<file name="text.png" server="ftp.waverleymrc.org.au" local="128481368270000000" remote="128663408400000000" />
<file name="video.png" server="ftp.waverleymrc.org.au" local="128481368270000000" remote="128663408400000000" />
<file name="zip.png" server="ftp.waverleymrc.org.au" local="128481368270000000" remote="128663409000000000" />
</dwsync>